animategv/__init__.py
animategv/__main__.py
animategv/action.py
animategv/animation.py
animategv/jupyter.py
animategv/render.py
AnimateGraphViz-1.1.1.dist-info/LICENSE.txt
AnimateGraphViz-1.1.1.dist-info/METADATA
AnimateGraphViz-1.1.1.dist-info/WHEEL
AnimateGraphViz-1.1.1.dist-info/top_level.txt
AnimateGraphViz-1.1.1.dist-info/RECORD
